scrapy_scrapingbee/__init__.py
scrapy_scrapingbee/middleware.py
scrapy_scrapingbee/request.py
scrapy_scrapingbee/spider.py
scrapy_scrapingbee-0.0.5.dist-info/METADATA
scrapy_scrapingbee-0.0.5.dist-info/WHEEL
scrapy_scrapingbee-0.0.5.dist-info/top_level.txt
scrapy_scrapingbee-0.0.5.dist-info/RECORD
