Metadata-Version: 2.1
Name: scrapy-scrapingbee
Version: 0.0.5
Summary: JavaScript support and proxy rotation for Scrapy with ScrapingBee
Home-page: https://github.com/scrapingbee/scrapy-scrapingbee
Author: Ari Bajo Rouvinen
Maintainer: Pierre de Wulf
Maintainer-email: hello@scrapingbee.com
License: MIT
Platform: UNKNOWN
Classifier: License :: OSI Approved :: MIT License
Classifier: Programming Language :: Python
Classifier: Programming Language :: Python :: 3
Classifier: Programming Language :: Python :: 3.5
Classifier: Programming Language :: Python :: 3.6
Classifier: Framework :: Scrapy
Classifier: Topic :: Software Development :: Libraries :: Application Frameworks
Classifier: Topic :: Software Development :: Libraries :: Python Modules
Requires-Python: >=3.5
Requires-Dist: scrapy
